impact_factor/__init__.py
impact_factor/version.json
impact_factor/bin/__init__.py
impact_factor/bin/_build.py
impact_factor/bin/_filter.py
impact_factor/bin/_search.py
impact_factor/bin/cli.py
impact_factor/core/__init__.py
impact_factor/core/database.py
impact_factor/core/factor.py
impact_factor/core/nlmcatalog.py
impact_factor/data/2022_JCR_IF.xlsx
impact_factor/data/CopyofImpactFactor2024.xlsx
impact_factor/data/impact_factor.sqlite3
impact_factor/util/__init__.py
impact_factor/util/excel_parser.py
impact_factor-1.1.2.dist-info/METADATA
impact_factor-1.1.2.dist-info/WHEEL
impact_factor-1.1.2.dist-info/entry_points.txt
impact_factor-1.1.2.dist-info/top_level.txt
impact_factor-1.1.2.dist-info/RECORD
