Metadata-Version: 2.1
Name: impact-factor
Version: 1.1.2
Summary: Impact Factor Toolkits
Home-page: https://github.com/suqingdong/impact_factor
Author: suqingdong
Author-email: suqingdong1114@gmail.com
License: MIT License
Project-URL: Documentation, https://impact_factor.readthedocs.io
Project-URL: Tracker, https://github.com/suqingdong/impact_factor/issues
Platform: UNKNOWN
Classifier: Development Status :: 5 - Production/Stable
Classifier: Operating System :: OS Independent
Classifier: Intended Audience :: Developers
Classifier: License :: OSI Approved :: MIT License
Classifier: Programming Language :: Python
Classifier: Programming Language :: Python :: 3
Classifier: Programming Language :: Python :: 3 :: Only
Classifier: Programming Language :: Python :: 3.8
Classifier: Programming Language :: Python :: 3.9
Classifier: Topic :: Software Development :: Libraries
Requires-Dist: lxml
Requires-Dist: click
Requires-Dist: openpyxl
Requires-Dist: pygments
Requires-Dist: webrequests
Requires-Dist: sql-manager
